django_ltree_field/__init__.py
django_ltree_field/apps.py
django_ltree_field/fields.py
django_ltree_field/functions.py
django_ltree_field/models.py
django_ltree_field/validators.py
django_ltree_field/version.py
django_ltree_field/migrations/0001_initial.py
django_ltree_field/migrations/__init__.py
django_ltree_field/test_utils/__init__.py
django_ltree_field/test_utils/test_app/__init__.py
django_ltree_field/test_utils/test_app/admin.py
django_ltree_field/test_utils/test_app/apps.py
django_ltree_field/test_utils/test_app/models.py
django_ltree_field/test_utils/test_app/migrations/0001_initial.py
django_ltree_field/test_utils/test_app/migrations/0002_auto_20210330_0306.py
django_ltree_field/test_utils/test_app/migrations/0003_auto_20210330_0308.py
django_ltree_field/test_utils/test_app/migrations/__init__.py
django_ltree_field-0.1.7.dist-info/AUTHORS.rst
django_ltree_field-0.1.7.dist-info/LICENSE
django_ltree_field-0.1.7.dist-info/METADATA
django_ltree_field-0.1.7.dist-info/WHEEL
django_ltree_field-0.1.7.dist-info/top_level.txt
django_ltree_field-0.1.7.dist-info/RECORD
