Metadata-Version: 2.1
Name: django-ltree-field
Version: 0.1.7
Summary: LTreeField for Django
Home-page: https://github.com/john-parton/django-ltree-field/
Author: John Parton
License: BSD 3-Clause License
Platform: UNKNOWN
Classifier: Development Status :: 3 - Alpha
Classifier: Framework :: Django
Classifier: License :: OSI Approved :: BSD License
Classifier: Natural Language :: English
Classifier: Programming Language :: Python :: 3.6
Classifier: Programming Language :: Python :: 3.7
Classifier: Programming Language :: Python :: 3.8
License-File: LICENSE
License-File: AUTHORS.rst
